molingtool_sync/__init__.py
molingtool_sync-1.0.1.dist-info/METADATA
molingtool_sync-1.0.1.dist-info/WHEEL
molingtool_sync-1.0.1.dist-info/top_level.txt
molingtool_sync-1.0.1.dist-info/RECORD
